{"id": "MAT497Y1S20201", "code": "MAT497Y1S", "name": "Research Project in Mathematics", "description": "Independent research under the direction of a faculty member. Not eligible for CR/NCR option. Similar workload to a 72L course.", "division": "Faculty of Arts and Science", "department": "Mathematics", "prerequisites": "Minimum GPA of 3.5 in APM and MAT courses. Permission of the Associate Chair for Undergraduate Studies and of the prospective supervisor", "exclusions": "", "level": 400, "campus": "UTSG", "term": "2020 Winter", "breadths": [5], "meeting_sections": [{"code": "L0101", "instructors": [], "times": [], "size": 10, "enrolment": 0}]}